{
	"id": "b3eedb92-dfe5-410b-b947-297e984806a4",
	"name": "Simple Jobportal MX100",
	"values": [
		{
			"key": "url",
			"value": "",
			"type": "default",
			"enabled": true
		},
		{
			"key": "candidate_token",
			"value": "",
			"type": "default",
			"enabled": true
		},
		{
			"key": "employer_token",
			"value": "",
			"type": "default",
			"enabled": true
		}
	],
	"_postman_variable_scope": "environment",
	"_postman_exported_at": "2025-11-15T17:15:01.025Z",
	"_postman_exported_using": "Postman/11.71.7"
}